posedr.py
posedr-0.0.1.dist-info/LICENSE.txt
posedr-0.0.1.dist-info/METADATA
posedr-0.0.1.dist-info/WHEEL
posedr-0.0.1.dist-info/top_level.txt
posedr-0.0.1.dist-info/RECORD
