Metadata-Version: 2.1
Name: posedr
Version: 0.0.1
Summary: Pose Detection By mediapipe and cv2
Author: Karthikeyan
Keywords: Human pose estimation,Body tracking,Image processing
Classifier: Programming Language :: Python :: 3
Classifier: License :: OSI Approved :: MIT License
Classifier: Operating System :: OS Independent
Requires-Python: >=3.6
License-File: LICENSE.txt
Requires-Dist: opencv-python
Requires-Dist: mediapipe
